{
  "-1003915416039": {
    "nombre": "3Pagos Arg Comp.",
    "semana_actual": "Semana 17/06/2026",
    "registros": [],
    "errores": [],
    "chat_id": -1003915416039,
    "ultimo_resumen_idx": 0,
    "total_mensual": 52724974.65,
    "mes_actual": "06/2026"
  },
  "531707598": {
    "nombre": "Grupo",
    "semana_actual": "Semana 17/06/2026",
    "registros": [],
    "errores": [],
    "chat_id": 531707598,
    "ultimo_resumen_idx": 0,
    "total_mensual": 0.0,
    "mes_actual": ""
  },
  "-1004459084298": {
    "nombre": "Pagos Arg provisional",
    "semana_actual": "Semana 17/06/2026",
    "registros": [],
    "errores": [],
    "chat_id": -1004459084298,
    "ultimo_resumen_idx": 0,
    "total_mensual": 0.0,
    "mes_actual": "06/2026"
  },
  "-5484184532": {
    "nombre": "Xxxxxpro y Api-Agi",
    "semana_actual": "Semana 17/06/2026",
    "registros": [],
    "errores": [],
    "chat_id": -5484184532,
    "ultimo_resumen_idx": 0,
    "total_mensual": 0.0,
    "mes_actual": "06/2026"
  }
}